datasette_low_disk_space_hook/__init__.py
datasette_low_disk_space_hook/hookspecs.py
datasette_low_disk_space_hook-0.1.dist-info/LICENSE
datasette_low_disk_space_hook-0.1.dist-info/METADATA
datasette_low_disk_space_hook-0.1.dist-info/WHEEL
datasette_low_disk_space_hook-0.1.dist-info/entry_points.txt
datasette_low_disk_space_hook-0.1.dist-info/top_level.txt
datasette_low_disk_space_hook-0.1.dist-info/RECORD
