Metadata-Version: 2.1
Name: datasette-low-disk-space-hook
Version: 0.1
Summary: Datasette plugin providing the low_disk_space hook for other plugins to check for low disk space
Home-page: https://github.com/simonw/datasette-low-disk-space-hook
Author: Simon Willison
License: Apache License, Version 2.0
Project-URL: Issues, https://github.com/simonw/datasette-low-disk-space-hook/issues
Project-URL: CI, https://github.com/simonw/datasette-low-disk-space-hook/actions
Project-URL: Changelog, https://github.com/simonw/datasette-low-disk-space-hook/releases
Classifier: Framework :: Datasette
Classifier: License :: OSI Approved :: Apache Software License
Requires-Python: >=3.7
License-File: LICENSE
Requires-Dist: datasette
Provides-Extra: test
Requires-Dist: pytest ; extra == 'test'
Requires-Dist: pytest-asyncio ; extra == 'test'
